Workbook

Sheet Hoja1
A1: ID | B1: Moneda | C1: Reglas de lista de precios/ID | D1: Reglas de lista de precios/Mostrar aplicado en | E1: Reglas de lista de precios/Según | F1: Reglas de lista de precios/Producto/ID | G1: Reglas de lista de precios/Producto | H1: Reglas de lista de precios/Precio fijo | I1: Reglas de lista de precios/Precio de descuento | J1: Reglas de lista de precios/Calcular el precio | K1: Reglas de lista de precios/Aplicar en | L1: Reglas de lista de precios/Utilidad sobre el costo (%) | M1: Reglas de lista de precios/Producto/Referencia interna | N1: Reglas de lista de precios/Producto/Categoría del producto | O1: Familia (auto) | P1: Categoría de descuento
A2: __import__.__import__pricelists_mo_230625__0006 | B2: MXM | C2: __export__.product_pricelist_item_1649017_11d61724 | D2: Producto | E2: Precio de venta | F2: __export__.product_template_447866_bb13b66b | G2: [M178-227-NH] LAMBRIN INTERIOR NEGRO HUMO 16.8X2.90 (M178-227-NH) | H2: 150.8621 | I2: 0 | J2: Precio fijo | K2: Producto | L2: 0 | M2: M178-227-NH | N2: LAMBRIN CHINO | O2: LAMBRIN INTERIOR | P2: =IFERROR(IF(INDEX(Familias!$E$2:$E$25,MATCH($O2,Familias!$A$2:$A$25,0))="","",INDEX(Familias!$E$2:$E$25,MATCH($O2,Familias!$A$2:$A$25,0))),"")
A3: __import__.__import__pricelists_mo_230625__0006 | C3: __export__.product_pricelist_item_1649016_be4878d3 | D3: Producto | E3: Precio de venta | F3: __export__.product_template_447873_a89b2fe9 | G3: [ANG-M166-254] ANGULO PAROTA (ANG-M166-254) | H3: 72.42 | I3: 0 | J3: Precio fijo | K3: Producto | L3: 0 | M3: ANG-M166-254 | N3: LAMBRIN CHINO | O3: ANGULO LAMBRIN INTERIOR | P3: =IFERROR(IF(INDEX(Familias!$E$2:$E$25,MATCH($O3,Familias!$A$2:$A$25,0))="","",INDEX(Familias!$E$2:$E$25,MATCH($O3,Familias!$A$2:$A$25,0))),"")
A4: __import__.__import__pricelists_mo_230625__0006 | C4: __export__.product_pricelist_item_1649015_89cf628a | D4: Producto | E4: Precio de venta | F4: __export__.product_template_447872_eddc3a68 | G4: [ANG-148-227] ANGULO NEGRO HUMO (ANG-148-227) | H4: 72.42 | I4: 0 | J4: Precio fijo | K4: Producto | L4: 0 | M4: ANG-148-227 | N4: LAMBRIN CHINO | O4: ANGULO LAMBRIN INTERIOR | P4: =IFERROR(IF(INDEX(Familias!$E$2:$E$25,MATCH($O4,Familias!$A$2:$A$25,0))="","",INDEX(Familias!$E$2:$E$25,MATCH($O4,Familias!$A$2:$A$25,0))),"")
A5: __import__.__import__pricelists_mo_230625__0006 | C5: __export__.product_pricelist_item_1649014_1cce08f4 | D5: Producto | E5: Precio de venta | F5: __export__.product_template_447875_225ff4d7 | G5: [ANG-M127-364] ANGULO GRIS OXFORD (ANG-M127-364) | H5: 72.42 | I5: 0 | J5: Precio fijo | K5: Producto | L5: 0 | M5: ANG-M127-364 | N5: LAMBRIN CHINO | O5: ANGULO LAMBRIN INTERIOR | P5: =IFERROR(IF(INDEX(Familias!$E$2:$E$25,MATCH($O5,Familias!$A$2:$A$25,0))="","",INDEX(Familias!$E$2:$E$25,MATCH($O5,Familias!$A$2:$A$25,0))),"")
A6: __import__.__import__pricelists_mo_230625__0006 | C6: __export__.product_pricelist_item_1649013_9936983b | D6: Producto | E6: Precio de venta | F6: __export__.product_template_447874_9603f998 | G6: [ANG-9451-01] ANGULO CAOBA (ANG-9451-01) | H6: 72.42 | I6: 0 | J6: Precio fijo | K6: Producto | L6: 0 | M6: ANG-9451-01 | N6: LAMBRIN CHINO | O6: ANGULO LAMBRIN INTERIOR | P6: =IFERROR(IF(INDEX(Familias!$E$2:$E$25,MATCH($O6,Familias!$A$2:$A$25,0))="","",INDEX(Familias!$E$2:$E$25,MATCH($O6,Familias!$A$2:$A$25,0))),"")
A7: __import__.__import__pricelists_mo_230625__0006 | C7: __export__.product_pricelist_item_1649012_71da9613 | D7: Producto | E7: Precio de venta | F7: __export__.product_template_447870_44e99e40 | G7: [1689-2-PORTORO] MARMOL PORTORO 2.44X1.22 (1689-2-PORTORO) | H7: 690.51724 | I7: 0 | J7: Precio fijo | K7: Producto | L7: 0 | M7: 1689-2-PORTORO | N7: LAMBRIN CHINO | O7: MARMOL SINTETICO | P7: =IFERROR(IF(INDEX(Familias!$E$2:$E$25,MATCH($O7,Familias!$A$2:$A$25,0))="","",INDEX(Familias!$E$2:$E$25,MATCH($O7,Familias!$A$2:$A$25,0))),"")
A8: __import__.__import__pricelists_mo_230625__0006 | C8: __export__.product_pricelist_item_1649011_e39a3d18 | D8: Producto | E8: Precio de venta | F8: __export__.product_template_447869_b66baaaa | G8: [1659-IMPERIAL] MARMOL IMPERIAL BROWN 2.44X1.22 (1659-IMPERIAL) | H8: 690.51724 | I8: 0 | J8: Precio fijo | K8: Producto | L8: 0 | M8: 1659-IMPERIAL | N8: LAMBRIN CHINO | O8: MARMOL SINTETICO | P8: =IFERROR(IF(INDEX(Familias!$E$2:$E$25,MATCH($O8,Familias!$A$2:$A$25,0))="","",INDEX(Familias!$E$2:$E$25,MATCH($O8,Familias!$A$2:$A$25,0))),"")
A9: __import__.__import__pricelists_mo_230625__0006 | C9: __export__.product_pricelist_item_1649010_c37a3469 | D9: Producto | E9: Precio de venta | F9: __export__.product_template_447867_54d3fd69 | G9: [1670-1] MARMOL CALACATA GOLD 2.44X1.22 (1670-1) | H9: 690.51724 | I9: 0 | J9: Precio fijo | K9: Producto | L9: 0 | M9: 1670-1 | N9: LAMBRIN CHINO | O9: MARMOL SINTETICO | P9: =IFERROR(IF(INDEX(Familias!$E$2:$E$25,MATCH($O9,Familias!$A$2:$A$25,0))="","",INDEX(Familias!$E$2:$E$25,MATCH($O9,Familias!$A$2:$A$25,0))),"")
A10: __import__.__import__pricelists_mo_230625__0006 | C10: __export__.product_pricelist_item_1649009_5351a5f5 | D10: Producto | E10: Precio de venta | F10: __export__.product_template_447871_9c7d6dc4 | G10: [1683-DUNE] MARMOL BLACK DUNE 2.44X1.22 (1683-BLACK) | H10: 690.51724 | I10: 0 | J10: Precio fijo | K10: Producto | L10: 0 | M10: 1683-DUNE | N10: LAMBRIN CHINO | O10: MARMOL SINTETICO | P10: =IFERROR(IF(INDEX(Familias!$E$2:$E$25,MATCH($O10,Familias!$A$2:$A$25,0))="","",INDEX(Familias!$E$2:$E$25,MATCH($O10,Familias!$A$2:$A$25,0))),"")
A11: __import__.__import__pricelists_mo_230625__0006 | C11: __export__.product_pricelist_item_1645634_ce911248 | D11: Producto | E11: Precio de venta | F11: __import__.product_template_130625_edaf1167 | G11: [BUY-PL04] Placa Embozada 3mm Pizarra 8650, 1.20 x 2.80 m (BUY-PL04) | H11: 735.44 | I11: 0 | J11: Precio fijo | K11: Producto | L11: 0 | M11: BUY-PL04 | N11: LAMBRIN | O11: PLACA PVC | P11: =IFERROR(IF(INDEX(Familias!$E$2:$E$25,MATCH($O11,Familias!$A$2:$A$25,0))="","",INDEX(Familias!$E$2:$E$25,MATCH($O11,Familias!$A$2:$A$25,0))),"")
A12: __import__.__import__pricelists_mo_230625__0006 | C12: __export__.product_pricelist_item_1645630_54310970 | D12: Producto | E12: Precio de venta | F12: __export__.product_template_443373_a3019cf6 | G12: [EA01] ESPEJO ACRILICO 2MM 1.22X2.44M TONO CLARO | H12: 1172.4137 | I12: 0 | J12: Precio fijo | K12: Producto | L12: 0 | M12: EA01 | N12: LAMBRIN CHINO | O12: ESPEJO ACRILICO | P12: =IFERROR(IF(INDEX(Familias!$E$2:$E$25,MATCH($O12,Familias!$A$2:$A$25,0))="","",INDEX(Familias!$E$2:$E$25,MATCH($O12,Familias!$A$2:$A$25,0))),"")
A13: __import__.__import__pricelists_mo_230625__0006 | C13: __export__.product_pricelist_item_1645620_ff5f2bab | D13: Producto | E13: Precio de venta | F13: __export__.product_template_443370_bb4362fa | G13: [LINUEZB] LAMBRIN INTERIOS S150 NUEZ BITONO 0.15X2.90M | H13: 150.862 | I13: 0 | J13: Precio fijo | K13: Producto | L13: 0 | M13: LINUEZB | N13: LAMBRIN CHINO | O13: LAMBRIN INTERIOR | P13: =IFERROR(IF(INDEX(Familias!$E$2:$E$25,MATCH($O13,Familias!$A$2:$A$25,0))="","",INDEX(Familias!$E$2:$E$25,MATCH($O13,Familias!$A$2:$A$25,0))),"")
A14: __import__.__import__pricelists_mo_230625__0006 | C14: __export__.product_pricelist_item_1645611_5b82c947 | D14: Producto | E14: Precio de venta | F14: __export__.product_template_443362_61f5794f | G14: [N-822-128-ROBLE] LAMBRIN INTERIOR 16.8X2.90 ROBLE | H14: 150.8621 | I14: 0 | J14: Precio fijo | K14: Producto | L14: 0 | M14: N-822-128-ROBLE | N14: LAMBRIN CHINO | O14: LAMBRIN INTERIOR | P14: =IFERROR(IF(INDEX(Familias!$E$2:$E$25,MATCH($O14,Familias!$A$2:$A$25,0))="","",INDEX(Familias!$E$2:$E$25,MATCH($O14,Familias!$A$2:$A$25,0))),"")
... A380: __import__.__import__pricelists_mo_230625__0006 | C380: __import__._import_pricelist_mo_items_id_1_250625_0001 | D380: Producto | E380: Precio de venta | F380: __import__.product_template_230625_0003 | G380: [BUY-MA98] Angulo Aluminio, Negro x 2.80 m (BUY-MA98) | H380: 115.63 | I380: 0 | J380: Precio fijo | K380: Producto | L380: 0 | M380: BUY-MA98 | N380: LAMBRIN | O380: ANGULO ALUMINIO | P380: =IFERROR(IF(INDEX(Familias!$E$2:$E$25,MATCH($O380,Familias!$A$2:$A$25,0))="","",INDEX(Familias!$E$2:$E$25,MATCH($O380,Familias!$A$2:$A$25,0))),"")

Sheet Familias
A1: Familia (auto) | B1: N° productos | C1: Precio mín | D1: Precio máx | E1: Categoría de descuento (llenar)
A2: MARMOL SINTETICO | B2: 60 | C2: 144.74 | D2: 819.83
A3: LAMBRIN INTERIOR | B3: 47 | C3: 150.86 | D3: 163.79
A4: ANGULO LAMBRIN INTERIOR | B4: 32 | C4: 72.42 | D4: 72.42
A5: PANEL CARBON | B5: 31 | C5: 969.53 | D5: 1225.05
A6: ESQUINERO ALUMINIO | B6: 23 | C6: 112.4 | D6: 157.12
A7: PLACA PVC | B7: 22 | C7: 512.67 | D7: 921.02
A8: MOLDURA ALUMINIO | B8: 22 | C8: 53.37 | D8: 147.17
A9: ZOCLO | B9: 16 | C9: 171.43 | D9: 171.43
A10: REDUCTOR | B10: 16 | C10: 155.25 | D10: 155.25
A11: PISO SPC | B11: 16 | C11: 659.48 | D11: 659.48
A12: JUNTA DE EXPANSION | B12: 16 | C12: 155.25 | D12: 155.25
A13: LAMBRIN EXTERIOR | B13: 13 | C13: 518.97 | D13: 556.04
... A25: CANAL DE TRACCION | B25: 1 | C25: 64.69 | D25: 64.69
A27: Llena la columna E (amarilla) con la categoría de escalonaje de descuento de cada familia; la columna P de Hoja1 se rellena sola por fórmula.
